dcflags/__init__.py
dcflags/_src.py
dcflags/py.typed
dcflags-0.1.0.dist-info/LICENSE
dcflags-0.1.0.dist-info/METADATA
dcflags-0.1.0.dist-info/WHEEL
dcflags-0.1.0.dist-info/top_level.txt
dcflags-0.1.0.dist-info/zip-safe
dcflags-0.1.0.dist-info/RECORD
