Metadata-Version: 2.1
Name: dcflags
Version: 0.1.0
Summary: Dataclass fields as cmd args and env vars
Home-page: https://github.com/adriansahlman/dcflags
Author: Adrian Sahlman
Author-email: adrian.sahlman@gmail.com
License: MIT
Keywords: parse arguments cmd command dataclass env environmental dcflags
Requires-Python: >=3.5
License-File: LICENSE
